roboto_ingestion_utils/__init__.py
roboto_ingestion_utils/csv.py
roboto_ingestion_utils/image_dir.py
roboto_ingestion_utils/ingestion_utils.py
roboto_ingestion_utils/metrics.py
roboto_ingestion_utils/timed.py
roboto_ingestion_utils/tests/__init__.py
roboto_ingestion_utils/tests/test_csv_utils.py
roboto_ingestion_utils/tests/test_img_utils.py
roboto_ingestion_utils/tests/test_utils.py
roboto_ingestion_utils-0.22.35.dist-info/LICENSE
roboto_ingestion_utils-0.22.35.dist-info/METADATA
roboto_ingestion_utils-0.22.35.dist-info/WHEEL
roboto_ingestion_utils-0.22.35.dist-info/top_level.txt
roboto_ingestion_utils-0.22.35.dist-info/RECORD
