Metadata-Version: 2.1
Name: roboto-ingestion-utils
Version: 0.22.35
Summary: Utility functions for roboto data ingestion
Home-page: https://github.com/roboto-ai/roboto-ingestion-utils
Download-URL: https://github.com/roboto-ai/roboto_ingestion_utils/archive/refs/tags/0.22.35.tar.gz
Author: Roboto Technologies
Author-email: yves@roboto.ai
Classifier: Programming Language :: Python :: 3
Classifier: License :: OSI Approved :: MIT License
Classifier: Operating System :: OS Independent
Requires-Python: >=3.9
License-File: LICENSE
Requires-Dist: roboto
Requires-Dist: pytest
Requires-Dist: mcap
Requires-Dist: genson
Requires-Dist: pandas
Requires-Dist: Pillow
Requires-Dist: mcap-protobuf-support
Requires-Dist: foxglove-schemas-protobuf
Requires-Dist: rosbags
Requires-Dist: mcap-ros2-support
Requires-Dist: rosbags-image
